debug_mode/__init__.py
debug_mode-0.1.1.dist-info/LICENSE
debug_mode-0.1.1.dist-info/METADATA
debug_mode-0.1.1.dist-info/WHEEL
debug_mode-0.1.1.dist-info/RECORD
