Metadata-Version: 2.1
Name: debug-mode
Version: 0.1.1
Summary: A powerful debug mode
License: MIT
Author: GCBallesteros
Author-email: dev+github@maxwellrules.com
Requires-Python: >=3.10,<4.0
Classifier: License :: OSI Approved :: MIT License
Classifier: Programming Language :: Python
Classifier: Programming Language :: Python :: 3
Classifier: Programming Language :: Python :: 3.10
Classifier: Programming Language :: Python :: 3.11
Classifier: Programming Language :: Python :: 3.12
Classifier: Topic :: Software Development
Classifier: Topic :: Software Development :: Debuggers
Classifier: Topic :: Software Development :: Testing
Requires-Dist: icecream (>=2.1.3,<3.0.0)
Requires-Dist: ipdb (>=0.13.13,<0.14.0)
Requires-Dist: wat-inspector (>=0.2.1,<0.3.0)
